_temporal_walk.cpython-312-darwin.so
temporal_walk/__init__.py
temporal_walk-0.5.6.dist-info/METADATA
temporal_walk-0.5.6.dist-info/WHEEL
temporal_walk-0.5.6.dist-info/top_level.txt
temporal_walk-0.5.6.dist-info/RECORD
