Metadata-Version: 2.2
Name: temporal_walk
Version: 0.5.6
Summary: A library to sample temporal walks from in-memory temporal graphs
Home-page: https://github.com/ashfaq1701/temporal_walk
Author: Ashfaq Salehin
Author-email: ashfaq.salehin1701@gmail.com
Requires-Python: >=3
Requires-Dist: pybind11>=2.6.0
Requires-Dist: numpy
Requires-Dist: networkx
Dynamic: author
Dynamic: author-email
Dynamic: description
Dynamic: description-content-type
Dynamic: home-page
Dynamic: requires-dist
Dynamic: requires-python
Dynamic: summary
